PygameLord/ChangeLog.txt
PygameLord/ColorChanger.py
PygameLord/ColorConstants.py
PygameLord/Font.py
PygameLord/Images.py
PygameLord/Loads.py
PygameLord/Manual.pdf
PygameLord/Motion.py
PygameLord/Sounds.py
PygameLord/Surface.py
PygameLord/__init__.py
PygameLord/Examples/Alien.py
PygameLord/Examples/Rotater.py
PygameLord/Examples/Images/Alien_Bolt.png
PygameLord/Examples/Images/Aliens.png
PygameLord/Examples/Images/Barrier.png
PygameLord/Examples/Images/Lazer.png
PygameLord/Examples/Images/Player.png
PygameLord/Examples/Images/Player_Bolt.png
PygameLord/Examples/Images/Tank.png
PygameLord/Examples/Sounds/Assistance.mp3
PygameLord/Examples/Sounds/Boom.wav
PygameLord/Examples/Sounds/Lazer.wav
PygameLord/Resorces/FONT LICENSE.TXT
PygameLord/Resorces/PxPlus_AmstradPC1512.ttf
PygameLord/Resorces/PygameLord.png
PygameLord-0.0.4.dist-info/LICENSE.txt
PygameLord-0.0.4.dist-info/METADATA
PygameLord-0.0.4.dist-info/WHEEL
PygameLord-0.0.4.dist-info/top_level.txt
PygameLord-0.0.4.dist-info/RECORD
