Metadata-Version: 2.1
Name: PygameLord
Version: 0.0.4
Summary: A pakage to help in game development with Pygame.
Home-page: UNKNOWN
Author: LordLynx
License: UNKNOWN
Platform: UNKNOWN
Classifier: Programming Language :: Python :: 3
Classifier: License :: OSI Approved :: MIT License
Classifier: Operating System :: OS Independent
Requires-Python: >=3.6
